stitch2d/__init__.py
stitch2d/__main__.py
stitch2d/mosaic.py
stitch2d/tile.py
stitch2d-1.2.dist-info/METADATA
stitch2d-1.2.dist-info/WHEEL
stitch2d-1.2.dist-info/entry_points.txt
stitch2d-1.2.dist-info/top_level.txt
stitch2d-1.2.dist-info/RECORD
