Metadata-Version: 2.1
Name: stitch2d
Version: 1.2
Summary: Stitches a 2D grid of images into a mosaic
Home-page: https://github.com/adamancer/stitch2d.git
Maintainer: Adam Mansur
Maintainer-email: mansura@si.edu
License: MIT
Platform: UNKNOWN
Classifier: License :: OSI Approved :: MIT License
Classifier: Programming Language :: Python :: 3.7
Classifier: Programming Language :: Python :: 3.8
Classifier: Programming Language :: Python :: 3.9
Classifier: Programming Language :: Python :: 3.10
Classifier: Topic :: Multimedia :: Graphics
Requires-Dist: joblib
Requires-Dist: numpy
Requires-Dist: opencv-python
Requires-Dist: scikit-image
